{
    "data": {
        "jurisdiction_ocdid": "ocd-jurisdiction/country:us/state:tx/place:moulton/government",
        "config": {
            "url": "https://www.cityofmoulton.com",
            "name": "Moulton town",
            "source_urls": null
        },
        "links": [
            {
                "url": "https://www.cityofmoulton.com/community",
                "status": "pending",
                "folder_name": "",
                "num_references": 3
            },
            {
                "url": "https://www.cityofmoulton.com/events-news-notices",
                "status": "pending",
                "folder_name": "",
                "num_references": 3
            },
            {
                "url": "https://www.cityofmoulton.com/resident-information",
                "status": "pending",
                "folder_name": "",
                "num_references": 3
            },
            {
                "url": "https://www.cityofmoulton.com/index.asp?SEC=533DA69D-C62C-400A-A9A9-9FC489DECCAC",
                "status": "pending",
                "folder_name": "",
                "num_references": 3
            },
            {
                "url": "https://www.cityofmoulton.com/index.asp?SEC=E0E379FA-2DFF-4E59-90F4-EAA6BD7D88B8",
                "status": "pending",
                "folder_name": "",
                "num_references": 3
            },
            {
                "url": "https://www.cityofmoulton.com/administration",
                "status": "pending",
                "folder_name": "",
                "num_references": 2
            },
            {
                "url": "https://www.cityofmoulton.com/index.asp?SEC=E495D540-7E29-4481-8B27-DC314371397D",
                "status": "pending",
                "folder_name": "",
                "num_references": 2
            },
            {
                "url": "https://www.cityofmoulton.com/index.asp?SEC=99C5E2BA-9D09-45CA-9044-0B5836CE1AE2&DE=1A25DA24-0F0E-4C51-A26A-769D969E8333",
                "status": "pending",
                "folder_name": "",
                "num_references": 2
            },
            {
                "url": "https://www.cityofmoulton.com/index.asp?SEC=99C5E2BA-9D09-45CA-9044-0B5836CE1AE2&DE=500BE545-7C2A-46F3-A901-DF4DE9F28A8D",
                "status": "pending",
                "folder_name": "",
                "num_references": 2
            },
            {
                "url": "https://www.cityofmoulton.com/index.asp?SEC=99C5E2BA-9D09-45CA-9044-0B5836CE1AE2&DE=7F06EA35-22E0-4211-8F77-83C1D4DFB40C",
                "status": "pending",
                "folder_name": "",
                "num_references": 2
            },
            {
                "url": "https://www.cityofmoulton.com/index.asp?SEC=99C5E2BA-9D09-45CA-9044-0B5836CE1AE2&DE=E3837947-D914-4B2F-938D-441AE24B60D1",
                "status": "pending",
                "folder_name": "",
                "num_references": 2
            },
            {
                "url": "https://www.cityofmoulton.com/index.asp?SEC=99C5E2BA-9D09-45CA-9044-0B5836CE1AE2&DE=68707A64-62C2-4176-B5E5-4AFED7812AB8",
                "status": "pending",
                "folder_name": "",
                "num_references": 2
            },
            {
                "url": "https://www.cityofmoulton.com/index.asp?SEC=99C5E2BA-9D09-45CA-9044-0B5836CE1AE2&DE=B214D342-AA39-4F6E-9679-067C56F948A5",
                "status": "pending",
                "folder_name": "",
                "num_references": 2
            },
            {
                "url": "https://www.cityofmoulton.com/index.asp?SEC=45C11CEC-0623-4223-BCD7-AD8DE7805375",
                "status": "pending",
                "folder_name": "",
                "num_references": 2
            },
            {
                "url": "https:////www.cityofmoulton.com/index.asp?SEC=3677BD80-9A1B-47E7-BABE-1571447B8821",
                "status": "pending",
                "folder_name": "",
                "num_references": 2
            },
            {
                "url": "https:////www.cityofmoulton.com/resident-information",
                "status": "pending",
                "folder_name": "",
                "num_references": 2
            },
            {
                "url": "https:////www.cityofmoulton.com/index.asp?SEC=A5C32337-7F1E-45A0-9C10-B00F1DF5CC11",
                "status": "pending",
                "folder_name": "",
                "num_references": 2
            },
            {
                "url": "https:////www.cityofmoulton.com/index.asp?SEC=E495D540-7E29-4481-8B27-DC314371397D",
                "status": "pending",
                "folder_name": "",
                "num_references": 2
            },
            {
                "url": "https:////www.cityofmoulton.com/index.asp?SEC=4CCD6624-0553-4A5A-BC21-B3A921A9BBCB",
                "status": "pending",
                "folder_name": "",
                "num_references": 2
            },
            {
                "url": "https://www.cityofmoulton.com/index.asp?SEC=99C5E2BA-9D09-45CA-9044-0B5836CE1AE2&Type=B_DIR",
                "status": "pending",
                "folder_name": "",
                "num_references": 1
            },
            {
                "url": "https://www.cityofmoulton.com/index.asp?SEC=4CCD6624-0553-4A5A-BC21-B3A921A9BBCB",
                "status": "pending",
                "folder_name": "",
                "num_references": 1
            },
            {
                "url": "https://www.cityofmoulton.com/index.asp?SEC=088D8A6F-CE2A-408B-B0F3-A686DF46C6E5",
                "status": "pending",
                "folder_name": "",
                "num_references": 1
            },
            {
                "url": "https://www.cityofmoulton.com/index.asp?SEC=C5F4052C-90CF-450B-8E2A-5B1535E0102D",
                "status": "pending",
                "folder_name": "",
                "num_references": 1
            },
            {
                "url": "https://www.cityofmoulton.com/index.asp?SEC=3677BD80-9A1B-47E7-BABE-1571447B8821",
                "status": "pending",
                "folder_name": "",
                "num_references": 1
            },
            {
                "url": "https://www.cityofmoulton.com/index.asp?SEC=939B0B4C-E404-40AD-834E-0A25AA2437FC",
                "status": "pending",
                "folder_name": "",
                "num_references": 1
            },
            {
                "url": "https://www.cityofmoulton.com/parks",
                "status": "pending",
                "folder_name": "",
                "num_references": 1
            },
            {
                "url": "https://www.cityofmoulton.com/public-works",
                "status": "pending",
                "folder_name": "",
                "num_references": 1
            },
            {
                "url": "https://www.cityofmoulton.com/police",
                "status": "pending",
                "folder_name": "",
                "num_references": 1
            },
            {
                "url": "https://www.cityofmoulton.com/business",
                "status": "pending",
                "folder_name": "",
                "num_references": 1
            },
            {
                "url": "https:////www.cityofmoulton.com/sitemap",
                "status": "pending",
                "folder_name": "",
                "num_references": 1
            },
            {
                "url": "https:////www.cityofmoulton.com/index.asp?SEC=E1219855-5170-4D5C-A486-D21CAE4AF100",
                "status": "pending",
                "folder_name": "",
                "num_references": 1
            },
            {
                "url": "https:////www.cityofmoulton.com/index.asp?SEC=22175C8A-C76B-4567-B3FC-E7BC125586C3",
                "status": "pending",
                "folder_name": "",
                "num_references": 1
            },
            {
                "url": "https:////www.cityofmoulton.com/index.asp?SEC=1781F94F-2CAB-4090-AB28-C7A5AFD4B9B5",
                "status": "pending",
                "folder_name": "",
                "num_references": 1
            },
            {
                "url": "https:////www.cityofmoulton.com/index.asp?SEC=D66BE9E4-D242-4126-A5B4-BDE32CDB90CC",
                "status": "pending",
                "folder_name": "",
                "num_references": 1
            },
            {
                "url": "https:////www.cityofmoulton.com/index.asp?SEC=66085ADB-564F-4593-A5F4-34AA462EA6BB",
                "status": "pending",
                "folder_name": "",
                "num_references": 1
            },
            {
                "url": "https:////www.cityofmoulton.com/index.asp?SEC=631EAEA6-EDEC-419C-AE1A-2B982278C156",
                "status": "pending",
                "folder_name": "",
                "num_references": 1
            },
            {
                "url": "https:////www.cityofmoulton.com/index.asp?SEC=5F18D8FF-4D6A-4343-A3E9-12BBE41F2FF6",
                "status": "pending",
                "folder_name": "",
                "num_references": 1
            },
            {
                "url": "https:////www.cityofmoulton.com/index.asp?SEC=7ED95929-81D7-4CF9-8F19-47146E30DD12",
                "status": "pending",
                "folder_name": "",
                "num_references": 1
            },
            {
                "url": "https:////www.cityofmoulton.com/index.asp?SEC=D1D2C0BA-587A-40C4-9C72-BF940FE848D2",
                "status": "pending",
                "folder_name": "",
                "num_references": 1
            },
            {
                "url": "https:////www.cityofmoulton.com/index.asp?SEC=506B5EC7-AFD7-4C46-80EB-BEC0793AAAF4",
                "status": "pending",
                "folder_name": "",
                "num_references": 1
            },
            {
                "url": "https:////www.cityofmoulton.com/index.asp?SEC=66FFF5CD-1216-4B2E-89CF-A8D618B89341",
                "status": "pending",
                "folder_name": "",
                "num_references": 1
            },
            {
                "url": "https:////www.cityofmoulton.com/index.asp?SEC=057F2C83-9C5A-480A-BF23-B24D7A89E66D",
                "status": "pending",
                "folder_name": "",
                "num_references": 1
            },
            {
                "url": "https:////www.cityofmoulton.com/index.asp?SEC=8427CF48-9903-483B-9040-0D40B2D997E5",
                "status": "pending",
                "folder_name": "",
                "num_references": 1
            },
            {
                "url": "https:////www.cityofmoulton.com/forms",
                "status": "pending",
                "folder_name": "",
                "num_references": 1
            },
            {
                "url": "https:////www.cityofmoulton.com/index.asp?SEC=088D8A6F-CE2A-408B-B0F3-A686DF46C6E5",
                "status": "pending",
                "folder_name": "",
                "num_references": 1
            },
            {
                "url": "https:////www.cityofmoulton.com/index.asp?SEC=647C0852-404D-4AF8-9A57-BB6E88C813D8",
                "status": "pending",
                "folder_name": "",
                "num_references": 1
            },
            {
                "url": "https:////www.cityofmoulton.com/index.asp?SEC=00836F87-1744-4AC7-8990-95BD4E26B47F",
                "status": "pending",
                "folder_name": "",
                "num_references": 1
            },
            {
                "url": "https:////www.cityofmoulton.com/index.asp?SEC=10AC592F-57FA-445C-9673-4B2B12CCCFB3",
                "status": "pending",
                "folder_name": "",
                "num_references": 1
            },
            {
                "url": "https:////www.cityofmoulton.com/fire",
                "status": "pending",
                "folder_name": "",
                "num_references": 1
            },
            {
                "url": "https:////www.cityofmoulton.com/court",
                "status": "pending",
                "folder_name": "",
                "num_references": 1
            },
            {
                "url": "https:////www.cityofmoulton.com/index.asp?SEC=621B1795-4C4F-45C9-85DC-8AD62B0F5B06",
                "status": "pending",
                "folder_name": "",
                "num_references": 1
            },
            {
                "url": "https:////www.cityofmoulton.com/index.asp?SEC=BC086695-3555-469F-8FE5-3B94F6D9C1EB",
                "status": "pending",
                "folder_name": "",
                "num_references": 1
            },
            {
                "url": "https:////www.cityofmoulton.com/index.asp?SEC=7C558817-30E9-40E2-9052-806ABD593A80",
                "status": "pending",
                "folder_name": "",
                "num_references": 1
            },
            {
                "url": "https:////www.cityofmoulton.com/index.asp?SEC=E8578E59-4892-4252-BBDA-1E36793BF284",
                "status": "pending",
                "folder_name": "",
                "num_references": 1
            },
            {
                "url": "https:////www.cityofmoulton.com/index.asp?SEC=7AFD6C55-7BA7-4B57-BD6A-A01CD47D2E8E",
                "status": "pending",
                "folder_name": "",
                "num_references": 1
            },
            {
                "url": "https:////www.cityofmoulton.com/index.asp?SEC=A0B3094F-7A51-4647-B585-41481C75190F",
                "status": "pending",
                "folder_name": "",
                "num_references": 1
            },
            {
                "url": "https:////www.cityofmoulton.com/index.asp?SEC=D89376F4-1FA1-4EEF-A25E-4E32427579FB",
                "status": "pending",
                "folder_name": "",
                "num_references": 1
            },
            {
                "url": "https:////www.cityofmoulton.com/index.asp?SEC=8FC7CA8F-4FD2-4127-9ECE-9373DFD1A8A4",
                "status": "pending",
                "folder_name": "",
                "num_references": 1
            },
            {
                "url": "https:////www.cityofmoulton.com/index.asp?SEC=8D07A795-1B22-437F-AF98-48C552C1AD67",
                "status": "pending",
                "folder_name": "",
                "num_references": 1
            },
            {
                "url": "https:////www.cityofmoulton.com/index.asp?SEC=9BB33CB8-9861-47E1-9795-C6A6AB44B6FE",
                "status": "pending",
                "folder_name": "",
                "num_references": 1
            },
            {
                "url": "https:////www.cityofmoulton.com/index.asp?SEC=12AB2A83-128F-4330-83F1-FF4EF5EB8D49",
                "status": "pending",
                "folder_name": "",
                "num_references": 1
            },
            {
                "url": "https:////www.cityofmoulton.com/index.asp?SEC=46E98B9A-8280-423A-B059-117B7BE74FDA",
                "status": "pending",
                "folder_name": "",
                "num_references": 1
            },
            {
                "url": "https:////www.cityofmoulton.com/index.asp?SEC=04E6F3B4-DBA1-4B8A-9B2A-636366B2F79D",
                "status": "pending",
                "folder_name": "",
                "num_references": 1
            },
            {
                "url": "https:////www.cityofmoulton.com/index.asp?SEC=7E963A6B-8D6C-42AC-9F7A-64E4B71EC2A1",
                "status": "pending",
                "folder_name": "",
                "num_references": 1
            },
            {
                "url": "https:////www.cityofmoulton.com/parks",
                "status": "pending",
                "folder_name": "",
                "num_references": 1
            },
            {
                "url": "https:////www.cityofmoulton.com/index.asp?SEC=B8072586-389F-453C-8815-CCF233FF0E54",
                "status": "pending",
                "folder_name": "",
                "num_references": 1
            },
            {
                "url": "https:////www.cityofmoulton.com/index.asp?SEC=A06C9053-AF79-4E0C-8DF9-6882D125ACA8",
                "status": "pending",
                "folder_name": "",
                "num_references": 1
            },
            {
                "url": "https:////www.cityofmoulton.com/index.asp?SEC=5FC8A9F7-5E02-4F5B-9329-BE6B8DCF2381",
                "status": "pending",
                "folder_name": "",
                "num_references": 1
            },
            {
                "url": "https:////www.cityofmoulton.com/index.asp?SEC=4018F946-47BE-4F06-848A-76804249099A",
                "status": "pending",
                "folder_name": "",
                "num_references": 1
            },
            {
                "url": "https:////www.cityofmoulton.com/public-works",
                "status": "pending",
                "folder_name": "",
                "num_references": 1
            },
            {
                "url": "https:////www.cityofmoulton.com/index.asp?SEC=9F20209F-B819-4DFF-9040-613FF2153070",
                "status": "pending",
                "folder_name": "",
                "num_references": 1
            },
            {
                "url": "https:////www.cityofmoulton.com/index.asp?SEC=FB7CBB76-46F4-4764-8C8E-8005E25F1F45",
                "status": "pending",
                "folder_name": "",
                "num_references": 1
            },
            {
                "url": "https:////www.cityofmoulton.com/index.asp?SEC=362E6DF6-B0BA-40CB-A9C2-130956796BDC",
                "status": "pending",
                "folder_name": "",
                "num_references": 1
            },
            {
                "url": "https:////www.cityofmoulton.com/index.asp?SEC=C998F34C-BFFC-4AF0-A691-C32F6514DAED",
                "status": "pending",
                "folder_name": "",
                "num_references": 1
            },
            {
                "url": "https:////www.cityofmoulton.com/index.asp?SEC=3FB4DEBB-45A7-4193-A482-47BEAEA9D362",
                "status": "pending",
                "folder_name": "",
                "num_references": 1
            },
            {
                "url": "https:////www.cityofmoulton.com/index.asp?SEC=A92EC588-E952-4829-A5BD-22071D1EADDD",
                "status": "pending",
                "folder_name": "",
                "num_references": 1
            },
            {
                "url": "https:////www.cityofmoulton.com/police",
                "status": "pending",
                "folder_name": "",
                "num_references": 1
            },
            {
                "url": "https:////www.cityofmoulton.com/index.asp?SEC=2E1CD30B-1351-40F7-BCC6-66F87DFBBBB2",
                "status": "pending",
                "folder_name": "",
                "num_references": 1
            },
            {
                "url": "https:////www.cityofmoulton.com/index.asp?SEC=F58455FF-6460-4AB0-82F0-6965C3FFB1A8",
                "status": "pending",
                "folder_name": "",
                "num_references": 1
            },
            {
                "url": "https:////www.cityofmoulton.com/index.asp?SEC=DCB22C97-C988-41D8-BECA-932C007138EF",
                "status": "pending",
                "folder_name": "",
                "num_references": 1
            },
            {
                "url": "https:////www.cityofmoulton.com/index.asp?SEC=F958EAAD-490E-4B9B-A55A-6A1BD9FE9250",
                "status": "pending",
                "folder_name": "",
                "num_references": 1
            },
            {
                "url": "https:////www.cityofmoulton.com/business",
                "status": "pending",
                "folder_name": "",
                "num_references": 1
            },
            {
                "url": "https:////www.cityofmoulton.com/index.asp?SEC=234C9C6D-DD18-43E5-88FE-E64528929091",
                "status": "pending",
                "folder_name": "",
                "num_references": 1
            },
            {
                "url": "https:////www.cityofmoulton.com/index.asp?SEC=74BE2D4B-CC2F-4AB9-A47B-A987EB492DC3",
                "status": "pending",
                "folder_name": "",
                "num_references": 1
            },
            {
                "url": "https:////www.cityofmoulton.com/index.asp?SEC=14B14B4A-0F49-4C51-A392-F9CBB68D37F0",
                "status": "pending",
                "folder_name": "",
                "num_references": 1
            },
            {
                "url": "https:////www.cityofmoulton.com/index.asp?SEC=124FB3DE-EDFC-4F83-ADF1-E0D82E92D968",
                "status": "pending",
                "folder_name": "",
                "num_references": 1
            },
            {
                "url": "https:////www.cityofmoulton.com/index.asp?SEC=536B2357-7A25-45A5-96D1-826C7F0037A5",
                "status": "pending",
                "folder_name": "",
                "num_references": 1
            },
            {
                "url": "https:////www.cityofmoulton.com/index.asp?SEC=646ECAF7-73CA-4C7F-BFDA-FB4E8362DA56",
                "status": "pending",
                "folder_name": "",
                "num_references": 1
            },
            {
                "url": "https:////www.cityofmoulton.com/index.asp?SEC=0C649CE0-7BB7-4883-B6DC-C3D5D978CCB5",
                "status": "pending",
                "folder_name": "",
                "num_references": 1
            },
            {
                "url": "https:////www.cityofmoulton.com/index.asp?SEC=B5514D03-E5EE-48C6-B34A-058084A6A37D",
                "status": "pending",
                "folder_name": "",
                "num_references": 1
            },
            {
                "url": "https:////www.cityofmoulton.com/index.asp?SEC=DC6DDCD3-C029-4215-BB3A-1F1CC7754AC4",
                "status": "pending",
                "folder_name": "",
                "num_references": 1
            },
            {
                "url": "https:////www.cityofmoulton.com/index.asp?SEC=74F95EC3-E99F-4CAC-BC8F-1ACFBA9EAAF3",
                "status": "pending",
                "folder_name": "",
                "num_references": 1
            },
            {
                "url": "https:////www.cityofmoulton.com/index.asp?SEC=73B29B34-8AF5-49EA-AB78-C946D66A3505",
                "status": "pending",
                "folder_name": "",
                "num_references": 1
            },
            {
                "url": "https:////www.cityofmoulton.com/index.asp?SEC=7708F4D4-5253-4F8A-849A-B57D176F34E3",
                "status": "pending",
                "folder_name": "",
                "num_references": 1
            },
            {
                "url": "https:////www.cityofmoulton.com/lodging",
                "status": "pending",
                "folder_name": "",
                "num_references": 1
            },
            {
                "url": "https:////www.cityofmoulton.com/index.asp?SEC=44C1FED4-73C5-49B0-B34B-2C8CDF4166CA",
                "status": "pending",
                "folder_name": "",
                "num_references": 1
            },
            {
                "url": "https:////www.cityofmoulton.com/index.asp?SEC=D8D82928-2980-4E8E-A603-75B9F1812645",
                "status": "pending",
                "folder_name": "",
                "num_references": 1
            },
            {
                "url": "https:////www.cityofmoulton.com/index.asp?SEC=6F38E47C-5BF4-478D-9F5A-780E5277A3DB",
                "status": "pending",
                "folder_name": "",
                "num_references": 1
            },
            {
                "url": "https:////www.cityofmoulton.com/index.asp?SEC=9078064B-B2A6-43A8-9DAF-F43E65A6F01C",
                "status": "pending",
                "folder_name": "",
                "num_references": 1
            },
            {
                "url": "https:////www.cityofmoulton.com/index.asp?SEC=4A347918-1642-4324-A2F1-A937C3D62846",
                "status": "pending",
                "folder_name": "",
                "num_references": 1
            },
            {
                "url": "https:////www.cityofmoulton.com/index.asp?SEC=FEDF7DC8-B5F5-4345-BA21-4E7A07598899",
                "status": "pending",
                "folder_name": "",
                "num_references": 1
            },
            {
                "url": "https:////www.cityofmoulton.com/index.asp?SEC=4C5CDE4D-DAAF-4905-8BD6-D79DDD2734FA",
                "status": "pending",
                "folder_name": "",
                "num_references": 1
            },
            {
                "url": "https:////www.cityofmoulton.com/index.asp?SEC=10C66BAA-D2E0-41E3-931F-DDC8CDD9A61E",
                "status": "pending",
                "folder_name": "",
                "num_references": 1
            },
            {
                "url": "https:////www.cityofmoulton.com/index.asp?SEC=F631AE9B-8A68-4C35-BE84-EE55A2423625",
                "status": "pending",
                "folder_name": "",
                "num_references": 1
            },
            {
                "url": "https:////www.cityofmoulton.com/index.asp?SEC=1733C635-38B9-4038-9022-8CE93D1131A0",
                "status": "pending",
                "folder_name": "",
                "num_references": 1
            },
            {
                "url": "https:////www.cityofmoulton.com/community-organizations",
                "status": "pending",
                "folder_name": "",
                "num_references": 1
            },
            {
                "url": "https:////www.cityofmoulton.com/events-news-notices",
                "status": "pending",
                "folder_name": "",
                "num_references": 1
            },
            {
                "url": "https:////www.cityofmoulton.com/index.asp?SEC=C5F4052C-90CF-450B-8E2A-5B1535E0102D",
                "status": "pending",
                "folder_name": "",
                "num_references": 1
            },
            {
                "url": "https:////www.cityofmoulton.com/index.asp?SEC=EABAC580-2BF2-4715-95DE-58FAFE22A7B2",
                "status": "pending",
                "folder_name": "",
                "num_references": 1
            },
            {
                "url": "https:////www.cityofmoulton.com/index.asp?SEC=939B0B4C-E404-40AD-834E-0A25AA2437FC",
                "status": "pending",
                "folder_name": "",
                "num_references": 1
            },
            {
                "url": "https:////www.cityofmoulton.com/index.asp?SEC=E0E379FA-2DFF-4E59-90F4-EAA6BD7D88B8",
                "status": "pending",
                "folder_name": "",
                "num_references": 1
            },
            {
                "url": "https:////www.cityofmoulton.com/index.asp?SEC=91382A42-82D6-462A-AE10-E6CC75554430",
                "status": "pending",
                "folder_name": "",
                "num_references": 1
            },
            {
                "url": "https:////www.cityofmoulton.com/index.asp?SEC=674B7305-BAC3-4F50-947D-F88762F25407",
                "status": "pending",
                "folder_name": "",
                "num_references": 1
            },
            {
                "url": "https:////www.cityofmoulton.com/index.asp?SEC=2C21F2D3-0DDC-42FB-AA59-A53553540357",
                "status": "pending",
                "folder_name": "",
                "num_references": 1
            },
            {
                "url": "https:////www.cityofmoulton.com/index.asp?SEC=02EEF3A8-89E9-4F4A-A33E-A6383CB517D0",
                "status": "pending",
                "folder_name": "",
                "num_references": 1
            },
            {
                "url": "https:////www.cityofmoulton.com/index.asp?SEC=67008A32-AAF6-4644-A3B8-6C1230B903E7",
                "status": "pending",
                "folder_name": "",
                "num_references": 1
            },
            {
                "url": "https:////www.cityofmoulton.com/index.asp?SEC=420B8188-86A1-43E5-A6DB-2513AC0D9744",
                "status": "pending",
                "folder_name": "",
                "num_references": 1
            },
            {
                "url": "https:////www.cityofmoulton.com/index.asp?SEC=10ED827C-BF8D-4D3D-876B-D43A923829E0",
                "status": "pending",
                "folder_name": "",
                "num_references": 1
            },
            {
                "url": "https:////www.cityofmoulton.com/index.asp?SEC=79ED2243-F0B6-4968-B4A9-1C5D48C26C5A",
                "status": "pending",
                "folder_name": "",
                "num_references": 1
            },
            {
                "url": "https:////www.cityofmoulton.com/pay-online",
                "status": "pending",
                "folder_name": "",
                "num_references": 1
            },
            {
                "url": "https:////www.cityofmoulton.com/index.asp?SEC=45C11CEC-0623-4223-BCD7-AD8DE7805375",
                "status": "pending",
                "folder_name": "",
                "num_references": 1
            },
            {
                "url": "https://www.cityofmoulton.com",
                "status": "processed_irrelevant",
                "folder_name": "www_cityofmoulton_com",
                "num_references": 0
            },
            {
                "url": "https://www.cityofmoulton.com/contact",
                "status": "processed_irrelevant",
                "folder_name": "www_cityofmoulton_com_contact",
                "num_references": 1
            },
            {
                "url": "https://www.cityofmoulton.com/about",
                "status": "processed_irrelevant",
                "folder_name": "www_cityofmoulton_com_about",
                "num_references": 2
            },
            {
                "url": "https://www.cityofmoulton.com/sitemap",
                "status": "processed_irrelevant",
                "folder_name": "www_cityofmoulton_com_sitemap",
                "num_references": 3
            },
            {
                "url": "https://www.cityofmoulton.com/government",
                "status": "processed_irrelevant",
                "folder_name": "www_cityofmoulton_com_government",
                "num_references": 2
            },
            {
                "url": "https:////www.cityofmoulton.com/index.asp?SEC=99C5E2BA-9D09-45CA-9044-0B5836CE1AE2",
                "status": "processed_heuristics_fail",
                "folder_name": "__www_cityofmoulton_com_index_asp?sec=99c5e2ba-9d09-45ca-9044-0b5836ce1ae2",
                "num_references": 3
            },
            {
                "url": "https:////www.cityofmoulton.com/index.asp?SEC=98E1DA1D-F8C6-48B6-8F84-5999B4823141",
                "status": "processed_irrelevant",
                "folder_name": "__www_cityofmoulton_com_index_asp?sec=98e1da1d-f8c6-48b6-8f84-5999b4823141",
                "num_references": 3
            },
            {
                "url": "https:////www.cityofmoulton.com/contact",
                "status": "processed_irrelevant",
                "folder_name": "__www_cityofmoulton_com_contact",
                "num_references": 3
            },
            {
                "url": "https://www.cityofmoulton.com/index.asp?SEC=99C5E2BA-9D09-45CA-9044-0B5836CE1AE2",
                "status": "done",
                "folder_name": "www_cityofmoulton_com_index_asp?sec=99c5e2ba-9d09-45ca-9044-0b5836ce1ae2",
                "num_references": 2
            },
            {
                "url": "https://www.cityofmoulton.com/index.asp?SEC=98E1DA1D-F8C6-48B6-8F84-5999B4823141",
                "status": "processed_irrelevant",
                "folder_name": "www_cityofmoulton_com_index_asp?sec=98e1da1d-f8c6-48b6-8f84-5999b4823141",
                "num_references": 3
            },
            {
                "url": "https:////www.cityofmoulton.com/government",
                "status": "processed_irrelevant",
                "folder_name": "__www_cityofmoulton_com_government",
                "num_references": 3
            },
            {
                "url": "https:////www.cityofmoulton.com/about",
                "status": "processed_irrelevant",
                "folder_name": "__www_cityofmoulton_com_about",
                "num_references": 3
            },
            {
                "url": "https://www.cityofmoulton.com/index.asp?SEC=2EFDC6E9-A807-4C32-B135-49EB4FE4F4AF",
                "status": "processed_irrelevant",
                "folder_name": "www_cityofmoulton_com_index_asp?sec=2efdc6e9-a807-4c32-b135-49eb4fe4f4af",
                "num_references": 2
            },
            {
                "url": "https:////www.cityofmoulton.com",
                "status": "processed_irrelevant",
                "folder_name": "__www_cityofmoulton_com",
                "num_references": 3
            },
            {
                "url": "https:////www.cityofmoulton.com/services",
                "status": "processed_irrelevant",
                "folder_name": "__www_cityofmoulton_com_services",
                "num_references": 3
            },
            {
                "url": "https:////www.cityofmoulton.com/administration",
                "status": "processed_irrelevant",
                "folder_name": "__www_cityofmoulton_com_administration",
                "num_references": 3
            },
            {
                "url": "https:////www.cityofmoulton.com/community",
                "status": "processed_irrelevant",
                "folder_name": "__www_cityofmoulton_com_community",
                "num_references": 3
            },
            {
                "url": "https://www.cityofmoulton.com/index.asp?SEC=A5C32337-7F1E-45A0-9C10-B00F1DF5CC11",
                "status": "processed_irrelevant",
                "folder_name": "www_cityofmoulton_com_index_asp?sec=a5c32337-7f1e-45a0-9c10-b00f1df5cc11",
                "num_references": 2
            },
            {
                "url": "https:////www.cityofmoulton.com/index.asp?SEC=2EFDC6E9-A807-4C32-B135-49EB4FE4F4AF",
                "status": "processed_irrelevant",
                "folder_name": "__www_cityofmoulton_com_index_asp?sec=2efdc6e9-a807-4c32-b135-49eb4fe4f4af",
                "num_references": 3
            },
            {
                "url": "https:////www.cityofmoulton.com/index.asp?SEC=533DA69D-C62C-400A-A9A9-9FC489DECCAC",
                "status": "processed_irrelevant",
                "folder_name": "__www_cityofmoulton_com_index_asp?sec=533da69d-c62c-400a-a9a9-9fc489deccac",
                "num_references": 3
            },
            {
                "url": "https://www.cityofmoulton.com/index.asp?SEC=8B055250-BAEB-4B37-9EB6-3AC0A4711D77",
                "status": "processed_irrelevant",
                "folder_name": "www_cityofmoulton_com_index_asp?sec=8b055250-baeb-4b37-9eb6-3ac0a4711d77",
                "num_references": 2
            },
            {
                "url": "https://www.cityofmoulton.com/services",
                "status": "processed_irrelevant",
                "folder_name": "www_cityofmoulton_com_services",
                "num_references": 3
            }
        ],
        "dead_urls": [],
        "prepare_pipeline_step": {
            "roles_hint": [],
            "identities": {},
            "source_urls": []
        },
        "research_municipality_step": {
            "people": [
                {
                    "name": "Mark Zimmerman",
                    "roles": [
                        "Mayor"
                    ],
                    "designations": []
                },
                {
                    "name": "Craig Hughes",
                    "roles": [
                        "Mayor Pro Tem",
                        "Council Member"
                    ],
                    "designations": []
                },
                {
                    "name": "Roberta Mejias",
                    "roles": [
                        "Council Member"
                    ],
                    "designations": [
                        "Place 3"
                    ]
                },
                {
                    "name": "Adam Nieto",
                    "roles": [
                        "Council Member"
                    ],
                    "designations": [
                        "Place 1"
                    ]
                },
                {
                    "name": "Kelley Moeller",
                    "roles": [
                        "Council Member"
                    ],
                    "designations": [
                        "Place 2"
                    ]
                },
                {
                    "name": "Jenna Harris",
                    "roles": [
                        "Council Member"
                    ],
                    "designations": [
                        "Place 4"
                    ]
                }
            ],
            "elected_officials": [
                {
                    "name": "Mark Zimmerman",
                    "roles": [
                        "Mayor"
                    ],
                    "designations": []
                },
                {
                    "name": "Craig Hughes",
                    "roles": [
                        "Mayor Pro Tem",
                        "Council Member"
                    ],
                    "designations": []
                },
                {
                    "name": "Roberta Mejias",
                    "roles": [
                        "Council Member"
                    ],
                    "designations": [
                        "Place 3"
                    ]
                },
                {
                    "name": "Adam Nieto",
                    "roles": [
                        "Council Member"
                    ],
                    "designations": [
                        "Place 1"
                    ]
                },
                {
                    "name": "Kelley Moeller",
                    "roles": [
                        "Council Member"
                    ],
                    "designations": [
                        "Place 2"
                    ]
                },
                {
                    "name": "Jenna Harris",
                    "roles": [
                        "Council Member"
                    ],
                    "designations": [
                        "Place 4"
                    ]
                }
            ],
            "notes": null,
            "origin_source": "google_gemini"
        },
        "search_links_step": {
            "search_link_pointer": 1,
            "search_engines": {
                "google": {
                    "links": [],
                    "status": "error"
                },
                "crawl": {
                    "links": [],
                    "status": "not_started"
                }
            },
            "error": "Google Search API key or search engine ID not set in environment variables."
        },
        "preprocess_page_content_step": {
            "elapsed_times": [
                25,
                24,
                24,
                23,
                23,
                24,
                24,
                24,
                24,
                24,
                23,
                24,
                24,
                24,
                23,
                24,
                23,
                23,
                24,
                24,
                23,
                23
            ],
            "total_elapsed_time_seconds": 521,
            "average_elapsed_time_seconds": 23
        },
        "process_page_content_step": {
            "raw_records_by_llm": {
                "google_gemini": {},
                "together_ai": {
                    "Mark Zimmerman": [
                        {
                            "name": "Mark Zimmerman",
                            "roles": [
                                "Mayor"
                            ],
                            "designations": [],
                            "phone": null,
                            "email": null,
                            "url": "https://www.cityofmoulton.com/index.asp?SEC=99C5E2BA-9D09-45CA-9044-0B5836CE1AE2&DE=1A25DA24-0F0E-4C51-A26A-769D969E8333",
                            "start_date": null,
                            "end_date": null,
                            "image": null,
                            "source_url": "https://www.cityofmoulton.com/index.asp?SEC=99C5E2BA-9D09-45CA-9044-0B5836CE1AE2"
                        }
                    ],
                    "Adam Nieto": [
                        {
                            "name": "Adam Nieto",
                            "roles": [
                                "City Council"
                            ],
                            "designations": [
                                "Position 1"
                            ],
                            "phone": null,
                            "email": null,
                            "url": "https://www.cityofmoulton.com/index.asp?SEC=99C5E2BA-9D09-45CA-9044-0B5836CE1AE2&DE=500BE545-7C2A-46F3-A901-DF4DE9F28A8D",
                            "start_date": null,
                            "end_date": null,
                            "image": null,
                            "source_url": "https://www.cityofmoulton.com/index.asp?SEC=99C5E2BA-9D09-45CA-9044-0B5836CE1AE2"
                        }
                    ],
                    "Kelley Moeller": [
                        {
                            "name": "Kelley Moeller",
                            "roles": [
                                "City Council"
                            ],
                            "designations": [
                                "Position 2"
                            ],
                            "phone": null,
                            "email": null,
                            "url": "https://www.cityofmoulton.com/index.asp?SEC=99C5E2BA-9D09-45CA-9044-0B5836CE1AE2&DE=7F06EA35-22E0-4211-8F77-83C1D4DFB40C",
                            "start_date": null,
                            "end_date": null,
                            "image": null,
                            "source_url": "https://www.cityofmoulton.com/index.asp?SEC=99C5E2BA-9D09-45CA-9044-0B5836CE1AE2"
                        }
                    ],
                    "Roberta Mejias": [
                        {
                            "name": "Roberta Mejias",
                            "roles": [
                                "City Council"
                            ],
                            "designations": [
                                "Position 3"
                            ],
                            "phone": null,
                            "email": null,
                            "url": "https://cityofmoulton.com/index.asp?SEC=99C5E2BA-9D09-45CA-9044-0B5836CE1AE2&DE=E3837947-D914-4B2F-938D-441AE24B60D1",
                            "start_date": null,
                            "end_date": null,
                            "image": null,
                            "source_url": "https://www.cityofmoulton.com/index.asp?SEC=99C5E2BA-9D09-45CA-9044-0B5836CE1AE2"
                        }
                    ],
                    "Jenna Harris": [
                        {
                            "name": "Jenna Harris",
                            "roles": [
                                "City Council"
                            ],
                            "designations": [
                                "Position 4"
                            ],
                            "phone": null,
                            "email": null,
                            "url": "https://www.cityofmoulton.com/index.asp?SEC=99C5E2BA-9D09-45CA-9044-0B5836CE1AE2&DE=68707A64-62C2-4176-B5E5-4AFED7812AB8",
                            "start_date": null,
                            "end_date": null,
                            "image": null,
                            "source_url": "https://www.cityofmoulton.com/index.asp?SEC=99C5E2BA-9D09-45CA-9044-0B5836CE1AE2"
                        }
                    ],
                    "Craig Hughes": [
                        {
                            "name": "Craig Hughes",
                            "roles": [
                                "City Council"
                            ],
                            "designations": [
                                "Position 5"
                            ],
                            "phone": null,
                            "email": null,
                            "url": "https://www.cityofmoulton.com/index.asp?SEC=99C5E2BA-9D09-45CA-9044-0B5836CE1AE2&DE=B214D342-AA39-4F6E-9679-067C56F948A5",
                            "start_date": null,
                            "end_date": null,
                            "image": null,
                            "source_url": "https://www.cityofmoulton.com/index.asp?SEC=99C5E2BA-9D09-45CA-9044-0B5836CE1AE2"
                        }
                    ]
                }
            },
            "records_by_llm": {
                "google_gemini": {},
                "together_ai": {
                    "Mark Zimmerman": [
                        {
                            "name": "Mark Zimmerman",
                            "roles": [
                                "Mayor"
                            ],
                            "designations": [],
                            "phone": null,
                            "email": null,
                            "url": "https://www.cityofmoulton.com/index.asp?SEC=99C5E2BA-9D09-45CA-9044-0B5836CE1AE2&DE=1A25DA24-0F0E-4C51-A26A-769D969E8333",
                            "start_date": null,
                            "end_date": null,
                            "image": null,
                            "source_url": "https://www.cityofmoulton.com/index.asp?SEC=99C5E2BA-9D09-45CA-9044-0B5836CE1AE2"
                        }
                    ],
                    "Adam Nieto": [
                        {
                            "name": "Adam Nieto",
                            "roles": [
                                "Council Member"
                            ],
                            "designations": [
                                "Position 1"
                            ],
                            "phone": null,
                            "email": null,
                            "url": "https://www.cityofmoulton.com/index.asp?SEC=99C5E2BA-9D09-45CA-9044-0B5836CE1AE2&DE=500BE545-7C2A-46F3-A901-DF4DE9F28A8D",
                            "start_date": null,
                            "end_date": null,
                            "image": null,
                            "source_url": "https://www.cityofmoulton.com/index.asp?SEC=99C5E2BA-9D09-45CA-9044-0B5836CE1AE2"
                        }
                    ],
                    "Kelley Moeller": [
                        {
                            "name": "Kelley Moeller",
                            "roles": [
                                "Council Member"
                            ],
                            "designations": [
                                "Position 2"
                            ],
                            "phone": null,
                            "email": null,
                            "url": "https://www.cityofmoulton.com/index.asp?SEC=99C5E2BA-9D09-45CA-9044-0B5836CE1AE2&DE=7F06EA35-22E0-4211-8F77-83C1D4DFB40C",
                            "start_date": null,
                            "end_date": null,
                            "image": null,
                            "source_url": "https://www.cityofmoulton.com/index.asp?SEC=99C5E2BA-9D09-45CA-9044-0B5836CE1AE2"
                        }
                    ],
                    "Roberta Mejias": [
                        {
                            "name": "Roberta Mejias",
                            "roles": [
                                "Council Member"
                            ],
                            "designations": [
                                "Position 3"
                            ],
                            "phone": null,
                            "email": null,
                            "url": "https://cityofmoulton.com/index.asp?SEC=99C5E2BA-9D09-45CA-9044-0B5836CE1AE2&DE=E3837947-D914-4B2F-938D-441AE24B60D1",
                            "start_date": null,
                            "end_date": null,
                            "image": null,
                            "source_url": "https://www.cityofmoulton.com/index.asp?SEC=99C5E2BA-9D09-45CA-9044-0B5836CE1AE2"
                        }
                    ],
                    "Jenna Harris": [
                        {
                            "name": "Jenna Harris",
                            "roles": [
                                "Council Member"
                            ],
                            "designations": [
                                "Position 4"
                            ],
                            "phone": null,
                            "email": null,
                            "url": "https://www.cityofmoulton.com/index.asp?SEC=99C5E2BA-9D09-45CA-9044-0B5836CE1AE2&DE=68707A64-62C2-4176-B5E5-4AFED7812AB8",
                            "start_date": null,
                            "end_date": null,
                            "image": null,
                            "source_url": "https://www.cityofmoulton.com/index.asp?SEC=99C5E2BA-9D09-45CA-9044-0B5836CE1AE2"
                        }
                    ],
                    "Craig Hughes": [
                        {
                            "name": "Craig Hughes",
                            "roles": [
                                "Council Member"
                            ],
                            "designations": [
                                "Position 5"
                            ],
                            "phone": null,
                            "email": null,
                            "url": "https://www.cityofmoulton.com/index.asp?SEC=99C5E2BA-9D09-45CA-9044-0B5836CE1AE2&DE=B214D342-AA39-4F6E-9679-067C56F948A5",
                            "start_date": null,
                            "end_date": null,
                            "image": null,
                            "source_url": "https://www.cityofmoulton.com/index.asp?SEC=99C5E2BA-9D09-45CA-9044-0B5836CE1AE2"
                        }
                    ]
                }
            },
            "progress": {
                "required_data": 6,
                "current_data": 0,
                "has_target_role": true,
                "has_target_designations": true
            }
        },
        "merge_records_within_llm_step": {
            "people_by_llm": {
                "google_gemini": [],
                "together_ai": [
                    {
                        "name": "Mark Zimmerman",
                        "other_names": [],
                        "roles": [
                            "Mayor"
                        ],
                        "designations": [],
                        "phones": [],
                        "emails": [],
                        "urls": [
                            "https://www.cityofmoulton.com/index.asp?SEC=99C5E2BA-9D09-45CA-9044-0B5836CE1AE2&DE=1A25DA24-0F0E-4C51-A26A-769D969E8333"
                        ],
                        "start_date": "",
                        "end_date": "",
                        "image": "",
                        "jurisdiction_ocdid": "ocd-jurisdiction/country:us/state:tx/place:moulton/government",
                        "cdn_image": "",
                        "source_urls": [
                            "https://www.cityofmoulton.com/index.asp?SEC=99C5E2BA-9D09-45CA-9044-0B5836CE1AE2"
                        ],
                        "updated_at": ""
                    },
                    {
                        "name": "Adam Nieto",
                        "other_names": [],
                        "roles": [
                            "Council Member"
                        ],
                        "designations": [
                            "Position 1"
                        ],
                        "phones": [],
                        "emails": [],
                        "urls": [
                            "https://www.cityofmoulton.com/index.asp?SEC=99C5E2BA-9D09-45CA-9044-0B5836CE1AE2&DE=500BE545-7C2A-46F3-A901-DF4DE9F28A8D"
                        ],
                        "start_date": "",
                        "end_date": "",
                        "image": "",
                        "jurisdiction_ocdid": "ocd-jurisdiction/country:us/state:tx/place:moulton/government",
                        "cdn_image": "",
                        "source_urls": [
                            "https://www.cityofmoulton.com/index.asp?SEC=99C5E2BA-9D09-45CA-9044-0B5836CE1AE2"
                        ],
                        "updated_at": ""
                    },
                    {
                        "name": "Kelley Moeller",
                        "other_names": [],
                        "roles": [
                            "Council Member"
                        ],
                        "designations": [
                            "Position 2"
                        ],
                        "phones": [],
                        "emails": [],
                        "urls": [
                            "https://www.cityofmoulton.com/index.asp?SEC=99C5E2BA-9D09-45CA-9044-0B5836CE1AE2&DE=7F06EA35-22E0-4211-8F77-83C1D4DFB40C"
                        ],
                        "start_date": "",
                        "end_date": "",
                        "image": "",
                        "jurisdiction_ocdid": "ocd-jurisdiction/country:us/state:tx/place:moulton/government",
                        "cdn_image": "",
                        "source_urls": [
                            "https://www.cityofmoulton.com/index.asp?SEC=99C5E2BA-9D09-45CA-9044-0B5836CE1AE2"
                        ],
                        "updated_at": ""
                    },
                    {
                        "name": "Roberta Mejias",
                        "other_names": [],
                        "roles": [
                            "Council Member"
                        ],
                        "designations": [
                            "Position 3"
                        ],
                        "phones": [],
                        "emails": [],
                        "urls": [
                            "https://cityofmoulton.com/index.asp?SEC=99C5E2BA-9D09-45CA-9044-0B5836CE1AE2&DE=E3837947-D914-4B2F-938D-441AE24B60D1"
                        ],
                        "start_date": "",
                        "end_date": "",
                        "image": "",
                        "jurisdiction_ocdid": "ocd-jurisdiction/country:us/state:tx/place:moulton/government",
                        "cdn_image": "",
                        "source_urls": [
                            "https://www.cityofmoulton.com/index.asp?SEC=99C5E2BA-9D09-45CA-9044-0B5836CE1AE2"
                        ],
                        "updated_at": ""
                    },
                    {
                        "name": "Jenna Harris",
                        "other_names": [],
                        "roles": [
                            "Council Member"
                        ],
                        "designations": [
                            "Position 4"
                        ],
                        "phones": [],
                        "emails": [],
                        "urls": [
                            "https://www.cityofmoulton.com/index.asp?SEC=99C5E2BA-9D09-45CA-9044-0B5836CE1AE2&DE=68707A64-62C2-4176-B5E5-4AFED7812AB8"
                        ],
                        "start_date": "",
                        "end_date": "",
                        "image": "",
                        "jurisdiction_ocdid": "ocd-jurisdiction/country:us/state:tx/place:moulton/government",
                        "cdn_image": "",
                        "source_urls": [
                            "https://www.cityofmoulton.com/index.asp?SEC=99C5E2BA-9D09-45CA-9044-0B5836CE1AE2"
                        ],
                        "updated_at": ""
                    },
                    {
                        "name": "Craig Hughes",
                        "other_names": [],
                        "roles": [
                            "Council Member"
                        ],
                        "designations": [
                            "Position 5"
                        ],
                        "phones": [],
                        "emails": [],
                        "urls": [
                            "https://www.cityofmoulton.com/index.asp?SEC=99C5E2BA-9D09-45CA-9044-0B5836CE1AE2&DE=B214D342-AA39-4F6E-9679-067C56F948A5"
                        ],
                        "start_date": "",
                        "end_date": "",
                        "image": "",
                        "jurisdiction_ocdid": "ocd-jurisdiction/country:us/state:tx/place:moulton/government",
                        "cdn_image": "",
                        "source_urls": [
                            "https://www.cityofmoulton.com/index.asp?SEC=99C5E2BA-9D09-45CA-9044-0B5836CE1AE2"
                        ],
                        "updated_at": ""
                    }
                ]
            },
            "unrecognized_roles": [],
            "excluded_people": []
        },
        "merge_records_across_llms_step": {
            "people": [
                {
                    "name": "Mark Zimmerman",
                    "other_names": [],
                    "roles": [
                        "mayor"
                    ],
                    "designations": [],
                    "phones": [],
                    "emails": [],
                    "urls": [
                        "https://www.cityofmoulton.com/index.asp?SEC=99C5E2BA-9D09-45CA-9044-0B5836CE1AE2&DE=1A25DA24-0F0E-4C51-A26A-769D969E8333"
                    ],
                    "start_date": "",
                    "end_date": "",
                    "image": "",
                    "jurisdiction_ocdid": "ocd-jurisdiction/country:us/state:tx/place:moulton/government",
                    "cdn_image": "",
                    "source_urls": [
                        "https://www.cityofmoulton.com/index.asp?SEC=99C5E2BA-9D09-45CA-9044-0B5836CE1AE2"
                    ],
                    "updated_at": "2026-04-01T20:51:47+00:00"
                },
                {
                    "name": "Adam Nieto",
                    "other_names": [],
                    "roles": [
                        "council member"
                    ],
                    "designations": [
                        "position 1"
                    ],
                    "phones": [],
                    "emails": [],
                    "urls": [
                        "https://www.cityofmoulton.com/index.asp?SEC=99C5E2BA-9D09-45CA-9044-0B5836CE1AE2&DE=500BE545-7C2A-46F3-A901-DF4DE9F28A8D"
                    ],
                    "start_date": "",
                    "end_date": "",
                    "image": "",
                    "jurisdiction_ocdid": "ocd-jurisdiction/country:us/state:tx/place:moulton/government",
                    "cdn_image": "",
                    "source_urls": [
                        "https://www.cityofmoulton.com/index.asp?SEC=99C5E2BA-9D09-45CA-9044-0B5836CE1AE2"
                    ],
                    "updated_at": "2026-04-01T20:51:47+00:00"
                },
                {
                    "name": "Kelley Moeller",
                    "other_names": [],
                    "roles": [
                        "council member"
                    ],
                    "designations": [
                        "position 2"
                    ],
                    "phones": [],
                    "emails": [],
                    "urls": [
                        "https://www.cityofmoulton.com/index.asp?SEC=99C5E2BA-9D09-45CA-9044-0B5836CE1AE2&DE=7F06EA35-22E0-4211-8F77-83C1D4DFB40C"
                    ],
                    "start_date": "",
                    "end_date": "",
                    "image": "",
                    "jurisdiction_ocdid": "ocd-jurisdiction/country:us/state:tx/place:moulton/government",
                    "cdn_image": "",
                    "source_urls": [
                        "https://www.cityofmoulton.com/index.asp?SEC=99C5E2BA-9D09-45CA-9044-0B5836CE1AE2"
                    ],
                    "updated_at": "2026-04-01T20:51:47+00:00"
                },
                {
                    "name": "Roberta Mejias",
                    "other_names": [],
                    "roles": [
                        "council member"
                    ],
                    "designations": [
                        "position 3"
                    ],
                    "phones": [],
                    "emails": [],
                    "urls": [
                        "https://cityofmoulton.com/index.asp?SEC=99C5E2BA-9D09-45CA-9044-0B5836CE1AE2&DE=E3837947-D914-4B2F-938D-441AE24B60D1"
                    ],
                    "start_date": "",
                    "end_date": "",
                    "image": "",
                    "jurisdiction_ocdid": "ocd-jurisdiction/country:us/state:tx/place:moulton/government",
                    "cdn_image": "",
                    "source_urls": [
                        "https://www.cityofmoulton.com/index.asp?SEC=99C5E2BA-9D09-45CA-9044-0B5836CE1AE2"
                    ],
                    "updated_at": "2026-04-01T20:51:47+00:00"
                },
                {
                    "name": "Jenna Harris",
                    "other_names": [],
                    "roles": [
                        "council member"
                    ],
                    "designations": [
                        "position 4"
                    ],
                    "phones": [],
                    "emails": [],
                    "urls": [
                        "https://www.cityofmoulton.com/index.asp?SEC=99C5E2BA-9D09-45CA-9044-0B5836CE1AE2&DE=68707A64-62C2-4176-B5E5-4AFED7812AB8"
                    ],
                    "start_date": "",
                    "end_date": "",
                    "image": "",
                    "jurisdiction_ocdid": "ocd-jurisdiction/country:us/state:tx/place:moulton/government",
                    "cdn_image": "",
                    "source_urls": [
                        "https://www.cityofmoulton.com/index.asp?SEC=99C5E2BA-9D09-45CA-9044-0B5836CE1AE2"
                    ],
                    "updated_at": "2026-04-01T20:51:47+00:00"
                },
                {
                    "name": "Craig Hughes",
                    "other_names": [],
                    "roles": [
                        "council member"
                    ],
                    "designations": [
                        "position 5"
                    ],
                    "phones": [],
                    "emails": [],
                    "urls": [
                        "https://www.cityofmoulton.com/index.asp?SEC=99C5E2BA-9D09-45CA-9044-0B5836CE1AE2&DE=B214D342-AA39-4F6E-9679-067C56F948A5"
                    ],
                    "start_date": "",
                    "end_date": "",
                    "image": "",
                    "jurisdiction_ocdid": "ocd-jurisdiction/country:us/state:tx/place:moulton/government",
                    "cdn_image": "",
                    "source_urls": [
                        "https://www.cityofmoulton.com/index.asp?SEC=99C5E2BA-9D09-45CA-9044-0B5836CE1AE2"
                    ],
                    "updated_at": "2026-04-01T20:51:47+00:00"
                }
            ]
        },
        "format_output_step": {
            "officials": [
                {
                    "name": "Mark Zimmerman",
                    "other_names": [],
                    "phones": [],
                    "emails": [],
                    "urls": [
                        "https://www.cityofmoulton.com/index.asp?SEC=99C5E2BA-9D09-45CA-9044-0B5836CE1AE2&DE=1A25DA24-0F0E-4C51-A26A-769D969E8333"
                    ],
                    "start_date": null,
                    "end_date": null,
                    "office": {
                        "name": "Mayor",
                        "division_ocdid": "ocd-division/country:us/state:tx/place:moulton"
                    },
                    "image": null,
                    "jurisdiction_ocdid": "ocd-jurisdiction/country:us/state:tx/place:moulton/government",
                    "cdn_image": null,
                    "source_urls": [
                        "https://www.cityofmoulton.com/index.asp?SEC=99C5E2BA-9D09-45CA-9044-0B5836CE1AE2"
                    ],
                    "updated_at": "2026-04-01T20:51:47+00:00",
                    "id": "559529d9-85ba-4b60-a75b-8def6d419bd6"
                },
                {
                    "name": "Adam Nieto",
                    "other_names": [],
                    "phones": [],
                    "emails": [],
                    "urls": [
                        "https://www.cityofmoulton.com/index.asp?SEC=99C5E2BA-9D09-45CA-9044-0B5836CE1AE2&DE=500BE545-7C2A-46F3-A901-DF4DE9F28A8D"
                    ],
                    "start_date": null,
                    "end_date": null,
                    "office": {
                        "name": "Council Member - Position 1",
                        "division_ocdid": "ocd-division/country:us/state:tx/place:moulton"
                    },
                    "image": null,
                    "jurisdiction_ocdid": "ocd-jurisdiction/country:us/state:tx/place:moulton/government",
                    "cdn_image": null,
                    "source_urls": [
                        "https://www.cityofmoulton.com/index.asp?SEC=99C5E2BA-9D09-45CA-9044-0B5836CE1AE2"
                    ],
                    "updated_at": "2026-04-01T20:51:47+00:00",
                    "id": "f6842aa3-a79a-4bef-89cb-77c1d28d8248"
                },
                {
                    "name": "Kelley Moeller",
                    "other_names": [],
                    "phones": [],
                    "emails": [],
                    "urls": [
                        "https://www.cityofmoulton.com/index.asp?SEC=99C5E2BA-9D09-45CA-9044-0B5836CE1AE2&DE=7F06EA35-22E0-4211-8F77-83C1D4DFB40C"
                    ],
                    "start_date": null,
                    "end_date": null,
                    "office": {
                        "name": "Council Member - Position 2",
                        "division_ocdid": "ocd-division/country:us/state:tx/place:moulton"
                    },
                    "image": null,
                    "jurisdiction_ocdid": "ocd-jurisdiction/country:us/state:tx/place:moulton/government",
                    "cdn_image": null,
                    "source_urls": [
                        "https://www.cityofmoulton.com/index.asp?SEC=99C5E2BA-9D09-45CA-9044-0B5836CE1AE2"
                    ],
                    "updated_at": "2026-04-01T20:51:47+00:00",
                    "id": "68973259-8b08-4174-8425-2e4342996f5c"
                },
                {
                    "name": "Roberta Mejias",
                    "other_names": [],
                    "phones": [],
                    "emails": [],
                    "urls": [
                        "https://cityofmoulton.com/index.asp?SEC=99C5E2BA-9D09-45CA-9044-0B5836CE1AE2&DE=E3837947-D914-4B2F-938D-441AE24B60D1"
                    ],
                    "start_date": null,
                    "end_date": null,
                    "office": {
                        "name": "Council Member - Position 3",
                        "division_ocdid": "ocd-division/country:us/state:tx/place:moulton"
                    },
                    "image": null,
                    "jurisdiction_ocdid": "ocd-jurisdiction/country:us/state:tx/place:moulton/government",
                    "cdn_image": null,
                    "source_urls": [
                        "https://www.cityofmoulton.com/index.asp?SEC=99C5E2BA-9D09-45CA-9044-0B5836CE1AE2"
                    ],
                    "updated_at": "2026-04-01T20:51:47+00:00",
                    "id": "75632601-bdfb-4931-88f1-6a9c8a484f3e"
                },
                {
                    "name": "Jenna Harris",
                    "other_names": [],
                    "phones": [],
                    "emails": [],
                    "urls": [
                        "https://www.cityofmoulton.com/index.asp?SEC=99C5E2BA-9D09-45CA-9044-0B5836CE1AE2&DE=68707A64-62C2-4176-B5E5-4AFED7812AB8"
                    ],
                    "start_date": null,
                    "end_date": null,
                    "office": {
                        "name": "Council Member - Position 4",
                        "division_ocdid": "ocd-division/country:us/state:tx/place:moulton"
                    },
                    "image": null,
                    "jurisdiction_ocdid": "ocd-jurisdiction/country:us/state:tx/place:moulton/government",
                    "cdn_image": null,
                    "source_urls": [
                        "https://www.cityofmoulton.com/index.asp?SEC=99C5E2BA-9D09-45CA-9044-0B5836CE1AE2"
                    ],
                    "updated_at": "2026-04-01T20:51:47+00:00",
                    "id": "cc05722e-8604-4269-9b7f-af042928fda5"
                },
                {
                    "name": "Craig Hughes",
                    "other_names": [],
                    "phones": [],
                    "emails": [],
                    "urls": [
                        "https://www.cityofmoulton.com/index.asp?SEC=99C5E2BA-9D09-45CA-9044-0B5836CE1AE2&DE=B214D342-AA39-4F6E-9679-067C56F948A5"
                    ],
                    "start_date": null,
                    "end_date": null,
                    "office": {
                        "name": "Council Member - Position 5",
                        "division_ocdid": "ocd-division/country:us/state:tx/place:moulton"
                    },
                    "image": null,
                    "jurisdiction_ocdid": "ocd-jurisdiction/country:us/state:tx/place:moulton/government",
                    "cdn_image": null,
                    "source_urls": [
                        "https://www.cityofmoulton.com/index.asp?SEC=99C5E2BA-9D09-45CA-9044-0B5836CE1AE2"
                    ],
                    "updated_at": "2026-04-01T20:51:47+00:00",
                    "id": "f16a71ef-07d9-4cca-ba23-bcd3d5f1db93"
                }
            ]
        },
        "review_output_step": {
            "issues": [],
            "people_by_source": [
                {
                    "name": "Adam Nieto",
                    "in_research": true,
                    "in_data": true
                },
                {
                    "name": "Craig Hughes",
                    "in_research": true,
                    "in_data": true
                },
                {
                    "name": "Jenna Harris",
                    "in_research": true,
                    "in_data": true
                },
                {
                    "name": "Kelley Moeller",
                    "in_research": true,
                    "in_data": true
                },
                {
                    "name": "Mark Zimmerman",
                    "in_research": true,
                    "in_data": true
                },
                {
                    "name": "Roberta Mejias",
                    "in_research": true,
                    "in_data": true
                }
            ],
            "origin_source": "google_gemini"
        },
        "send_success_step": null,
        "send_error_step": null,
        "error_step": null
    },
    "current_state": "SEND_SUCCESS",
    "request_id": "c7fd884d-111d-4057-9fdb-f00870ff31e7",
    "created_at": 1775075518.5197988,
    "updated_at": 1775076710.0482228,
    "progress": 27
}