[
  {
    "name": "Helen Tran",
    "roles": [
      "Mayor"
    ],
    "divisions": [
      "Null"
    ],
    "updated_at": "2025-07-17T17:53:41Z"
  },
  {
    "name": "Theodore Sanchez",
    "roles": [
      "Council Member"
    ],
    "divisions": [
      "Ward 1"
    ],
    "updated_at": "2025-07-17T17:53:41Z"
  },
  {
    "name": "Sandra Ibarra",
    "roles": [
      "Council Member"
    ],
    "divisions": [
      "Ward 2"
    ],
    "updated_at": "2025-07-17T17:53:41Z"
  },
  {
    "name": "Juan Figueroa",
    "roles": [
      "Council Member"
    ],
    "divisions": [
      "Ward 3"
    ],
    "updated_at": "2025-07-17T17:53:41Z"
  },
  {
    "name": "Fred Shorett",
    "roles": [
      "Council Member",
      "Mayor Pro Tempore"
    ],
    "divisions": [
      "Ward 4"
    ],
    "updated_at": "2025-07-17T17:53:41Z"
  },
  {
    "name": "Ben Reynoso",
    "roles": [
      "Council Member"
    ],
    "divisions": [
      "Ward 5"
    ],
    "updated_at": "2025-07-17T17:53:41Z"
  },
  {
    "name": "Kimberly Calvin",
    "roles": [
      "Council Member"
    ],
    "divisions": [
      "Ward 6"
    ],
    "updated_at": "2025-07-17T17:53:41Z"
  },
  {
    "name": "Damon L. Alexander",
    "roles": [
      "Council Member"
    ],
    "divisions": [
      "Ward 7"
    ],
    "updated_at": "2025-07-17T17:53:41Z"
  }
]